gluonts_customized/__init__.py
gluonts_customized/__main__.py
gluonts_customized/env.py
gluonts_customized/exceptions.py
gluonts_customized/gluonts_tqdm.py
gluonts_customized/itertools.py
gluonts_customized/json.py
gluonts_customized/json.pyi
gluonts_customized/maybe.py
gluonts_customized/pydantic.py
gluonts_customized/util.py
gluonts_customized/core/__init__.py
gluonts_customized/core/_base.py
gluonts_customized/core/component.py
gluonts_customized/core/py.typed
gluonts_customized/core/settings.py
gluonts_customized/core/serde/__init__.py
gluonts_customized/core/serde/_base.py
gluonts_customized/core/serde/_dataclass.py
gluonts_customized/core/serde/_json.py
gluonts_customized/core/serde/_parse.py
gluonts_customized/core/serde/flat.py
gluonts_customized/core/serde/np.py
gluonts_customized/core/serde/pd.py
gluonts_customized/dataset/__init__.py
gluonts_customized/dataset/common.py
gluonts_customized/dataset/field_names.py
gluonts_customized/dataset/hierarchical.py
gluonts_customized/dataset/jsonl.py
gluonts_customized/dataset/loader.py
gluonts_customized/dataset/multivariate_grouper.py
gluonts_customized/dataset/pandas.py
gluonts_customized/dataset/split.py
gluonts_customized/dataset/stat.py
gluonts_customized/dataset/util.py
gluonts_customized/dataset/arrow/__init__.py
gluonts_customized/dataset/arrow/__main__.py
gluonts_customized/dataset/arrow/dec.py
gluonts_customized/dataset/arrow/enc.py
gluonts_customized/dataset/arrow/file.py
gluonts_customized/dataset/artificial/__init__.py
gluonts_customized/dataset/artificial/_base.py
gluonts_customized/dataset/artificial/ar_p.py
gluonts_customized/dataset/artificial/recipe.py
gluonts_customized/dataset/repository/__init__.py
gluonts_customized/dataset/repository/_airpassengers.py
gluonts_customized/dataset/repository/_artificial.py
gluonts_customized/dataset/repository/_ercot.py
gluonts_customized/dataset/repository/_ett_small.py
gluonts_customized/dataset/repository/_gp_copula_2019.py
gluonts_customized-0.16.0.dist-info/METADATA
gluonts_customized-0.16.0.dist-info/WHEEL
gluonts_customized-0.16.0.dist-info/RECORD
