Metadata-Version: 2.4
Name: gluonts_customized
Version: 0.16.0
Summary: Add your description here
Requires-Python: >=3.12
Requires-Dist: cpflows<=0.1.2
Requires-Dist: lightning<=2.5.0.post0
Requires-Dist: matplotlib<=3.10.0
Requires-Dist: numba==0.61.0
Requires-Dist: numpy<=2.2.2
Requires-Dist: orjson<=3.10.15
Requires-Dist: pandas<=2.2.3
Requires-Dist: pyarrow<=19.0.0
Requires-Dist: pydantic<=2.10.6
Requires-Dist: scikit-learn<=1.6.1
Requires-Dist: statsmodels<=0.14.4
Requires-Dist: toolz<=1.0.0
Requires-Dist: torch<=2.6.0
Requires-Dist: tqdm<=4.67.1
Requires-Dist: ujson<=5.10.0
